[
  {
    "date": "2026-07-15",
    "changed": 0,
    "new": 0,
    "up": 0,
    "down": 0,
    "stable": 24,
    "trend_label": "Jour calme"
  },
  {
    "date": "2026-07-14",
    "changed": 0,
    "new": 0,
    "up": 0,
    "down": 0,
    "stable": 24,
    "trend_label": "Jour calme"
  },
  {
    "date": "2026-07-13",
    "changed": 0,
    "new": 0,
    "up": 0,
    "down": 0,
    "stable": 24,
    "trend_label": "Lundi calme"
  },
  {
    "date": "2026-07-12",
    "changed": 0,
    "new": 0,
    "up": 0,
    "down": 0,
    "stable": 24,
    "trend_label": "Dimanche calme"
  },
  {
    "date": "2026-07-11",
    "changed": 0,
    "new": 0,
    "up": 0,
    "down": 0,
    "stable": 24,
    "trend_label": "Jour calme"
  },
  {
    "date": "2026-07-10",
    "changed": 2,
    "new": 0,
    "up": 2,
    "down": 0,
    "stable": 22,
    "trend_label": "Votes du 9 juillet : Parlement UE fait avancer surveillance et euro numérique"
  },
  {
    "date": "2026-07-09",
    "changed": 0,
    "new": 0,
    "up": 0,
    "down": 0,
    "stable": 24,
    "trend_label": "Jour calme"
  },
  {
    "date": "2026-07-08",
    "changed": 0,
    "new": 0,
    "up": 0,
    "down": 0,
    "stable": 24,
    "trend_label": "Jour calme"
  },
  {
    "date": "2026-07-07",
    "changed": 0,
    "new": 0,
    "up": 0,
    "down": 0,
    "stable": 24,
    "trend_label": "Jour calme"
  },
  {
    "date": "2026-07-06",
    "changed": 0,
    "new": 0,
    "up": 0,
    "down": 0,
    "stable": 24,
    "trend_label": "Jour calme"
  },
  {
    "date": "2026-07-05",
    "changed": 0,
    "new": 0,
    "up": 0,
    "down": 0,
    "stable": 24,
    "trend_label": "Jour calme"
  },
  {
    "date": "2026-07-04",
    "changed": 0,
    "new": 0,
    "up": 0,
    "down": 0,
    "stable": 24,
    "trend_label": "Jour calme"
  },
  {
    "date": "2026-07-03",
    "changed": 0,
    "new": 0,
    "up": 0,
    "down": 0,
    "stable": 24,
    "trend_label": "Fin transitoire MiCA"
  },
  {
    "date": "2026-07-02",
    "changed": 0,
    "new": 0,
    "up": 0,
    "down": 0,
    "stable": 24,
    "trend_label": "Jour calme"
  },
  {
    "date": "2026-07-01",
    "changed": 0,
    "new": 0,
    "up": 0,
    "down": 0,
    "stable": 24,
    "trend_label": "Jour calme"
  },
  {
    "date": "2026-06-30",
    "changed": 0,
    "new": 0,
    "up": 0,
    "down": 0,
    "stable": 24,
    "trend_label": "5e trilogue CSAR sans accord"
  },
  {
    "date": "2026-06-29",
    "changed": 0,
    "new": 0,
    "up": 0,
    "down": 0,
    "stable": 24,
    "trend_label": "CSAR + Digital Omnibus : pas d'issue"
  },
  {
    "date": "2026-06-28",
    "changed": 0,
    "new": 0,
    "up": 0,
    "down": 0,
    "stable": 24,
    "trend_label": "Jour calme"
  },
  {
    "date": "2026-06-27",
    "changed": 1,
    "new": 0,
    "up": 1,
    "down": 0,
    "stable": 23,
    "trend_label": "Décrets quantiques US (Quantum Genesis) : Q-Day légèrement relevé, reste du tableau stable"
  },
  {
    "date": "2026-06-26",
    "changed": 0,
    "new": 0,
    "up": 0,
    "down": 0,
    "stable": 24,
    "trend_label": "Jour calme"
  },
  {
    "date": "2026-06-25",
    "changed": 0,
    "new": 0,
    "up": 0,
    "down": 0,
    "stable": 24,
    "trend_label": "Jour calme"
  },
  {
    "date": "2026-06-24",
    "changed": 1,
    "new": 0,
    "up": 1,
    "down": 0,
    "stable": 23,
    "trend_label": "Euro num. : vote ECON acquis (43-14), trilogues ouverts"
  },
  {
    "date": "2026-06-23",
    "changed": 0,
    "new": 0,
    "up": 0,
    "down": 0,
    "stable": 24,
    "trend_label": "Vote ECON euro num. en cours"
  },
  {
    "date": "2026-06-22",
    "changed": 0,
    "new": 0,
    "up": 0,
    "down": 0,
    "stable": 24,
    "trend_label": "Veille vote ECON"
  },
  {
    "date": "2026-06-21",
    "changed": 0,
    "new": 0,
    "up": 0,
    "down": 0,
    "stable": 24,
    "trend_label": "Jour calme"
  },
  {
    "date": "2026-06-20",
    "changed": 0,
    "new": 0,
    "up": 0,
    "down": 0,
    "stable": 24,
    "trend_label": "Jour calme"
  },
  {
    "date": "2026-06-18",
    "changed": 0,
    "new": 0,
    "up": 0,
    "down": 0,
    "stable": 24,
    "trend_label": "Jour calme"
  },
  {
    "date": "2026-06-17",
    "changed": 0,
    "new": 0,
    "up": 0,
    "down": 0,
    "stable": 24,
    "trend_label": "Jour calme"
  },
  {
    "date": "2026-06-16",
    "changed": 1,
    "new": 0,
    "up": 1,
    "down": 0,
    "stable": 23,
    "trend_label": "Euro numérique sur les rails"
  },
  {
    "date": "2026-06-15",
    "changed": 0,
    "new": 0,
    "up": 0,
    "down": 0,
    "stable": 24,
    "trend_label": "Veille calme"
  }
]